{
    "pex": [
        {
            "valor": 0,
            "data": "2021-07-26 02:42:34.923747"
        },
        {
            "valor": 0,
            "data": "2021-08-29 18:29:19.663461"
        }
    ],
    "andre": [
        {
            "valor": 0,
            "data": "2021-07-19 03:32:50.649209"
        },
        {
            "valor": 1,
            "data": "2021-07-19 03:35:32.822832"
        },
        {
            "valor": 2,
            "data": "2022-02-06 19:25:54.967829"
        },
        {
            "valor": 0,
            "data": "2022-02-06 19:30:52.108885"
        },
        {
            "valor": 2,
            "data": "2022-02-06 19:51:50.935096"
        },
        {
            "valor": 0,
            "data": "2022-02-06 20:12:32.486576"
        },
        {
            "valor": 2,
            "data": "2022-02-06 20:22:40.471942"
        },
        {
            "valor": 2,
            "data": "2022-02-06 20:23:58.168736"
        },
        {
            "valor": 1,
            "data": "2022-02-06 20:24:56.115236"
        },
        {
            "valor": 0,
            "data": "2022-02-13 19:00:51.334567"
        },
        {
            "valor": 2,
            "data": "2022-02-13 19:21:42.714495"
        },
        {
            "valor": 2,
            "data": "2022-02-13 19:24:00.414734"
        },
        {
            "valor": 2,
            "data": "2022-02-13 19:28:36.141233"
        },
        {
            "valor": 2,
            "data": "2022-02-13 19:56:26.520293"
        },
        {
            "valor": 2,
            "data": "2022-02-13 20:00:08.079916"
        },
        {
            "valor": 1,
            "data": "2022-02-13 20:04:47.185197"
        },
        {
            "valor": 1,
            "data": "2022-02-13 20:05:21.375087"
        },
        {
            "valor": 1,
            "data": "2022-02-13 20:06:57.484801"
        },
        {
            "valor": 1,
            "data": "2022-02-13 20:10:25.350811"
        },
        {
            "valor": 0,
            "data": "2022-02-20 21:01:01.864028"
        },
        {
            "valor": 1,
            "data": "2022-02-20 21:28:56.318871"
        },
        {
            "valor": 0,
            "data": "2022-02-20 21:35:37.749973"
        }
    ],
    "Rui": [
        {
            "valor": 0,
            "data": "2021-08-20 18:15:21.864750"
        },
        {
            "valor": 3,
            "data": "2022-02-06 20:27:23.071659"
        },
        {
            "valor": 3,
            "data": "2022-02-06 20:35:19.052200"
        },
        {
            "valor": 0,
            "data": "2022-02-20 19:05:49.760542"
        }
    ],
    "ro": [
        {
            "valor": 1,
            "data": "2021-07-25 19:33:50.719985"
        }
    ],
    "cat": [
        {
            "valor": 1,
            "data": "2021-07-25 18:54:38.135453"
        },
        {
            "valor": 0,
            "data": "2021-12-13 20:38:23.103030"
        },
        {
            "valor": 1,
            "data": "2021-12-13 20:39:33.953724"
        }
    ],
    "ver": [
        {
            "valor": 0,
            "data": "2021-07-19 03:36:42.575260"
        },
        {
            "valor": 1,
            "data": "2021-07-25 19:31:49.033072"
        },
        {
            "valor": 2,
            "data": "2022-02-13 19:35:29.030669"
        },
        {
            "valor": 1,
            "data": "2022-02-13 19:36:08.820674"
        }
    ],
    "dsfsdf": [
        {
            "valor": 1,
            "data": "2022-02-06 19:41:31.987632"
        }
    ],
    "ande": [
        {
            "valor": 3,
            "data": "2022-02-06 20:13:21.988324"
        }
    ],
    "Catarina": [
        {
            "valor": 3,
            "data": "2022-02-06 20:28:51.107998"
        }
    ],
    "Veronica": [
        {
            "valor": 2,
            "data": "2022-02-06 20:30:14.788223"
        },
        {
            "valor": 3,
            "data": "2022-02-06 20:30:50.068683"
        }
    ],
    "Veronica\\": [
        {
            "valor": 3,
            "data": "2022-02-06 20:34:27.688653"
        }
    ],
    "catarina": [
        {
            "valor": 2,
            "data": "2022-02-13 19:36:37.953520"
        },
        {
            "valor": 3,
            "data": "2022-02-13 19:37:06.125162"
        }
    ],
    "pedro": [
        {
            "valor": 3,
            "data": "2022-02-13 19:51:17.221236"
        }
    ],
    "fdgdfg": [
        {
            "valor": 0,
            "data": "2022-02-13 20:01:19.193285"
        }
    ],
    "asdasd": [
        {
            "valor": 0,
            "data": "2022-02-13 20:07:57.471912"
        },
        {
            "valor": 1,
            "data": "2022-02-13 20:08:20.338025"
        },
        {
            "valor": 0,
            "data": "2022-02-13 20:08:54.073902"
        },
        {
            "valor": 1,
            "data": "2022-02-13 20:09:02.448862"
        }
    ]
}